libecc/__init__.py
libecc/_libecc_cffi.cp310-mingw_x86_64.pyd
libecc/_libecc_cffi.cpython-310-x86_64-linux-gnu.so
libecc/_libecc_cffi.cpython-311-darwin.so
libecc/libecc.py
libecc-1.1.0.dist-info/LICENSE
libecc-1.1.0.dist-info/METADATA
libecc-1.1.0.dist-info/WHEEL
libecc-1.1.0.dist-info/top_level.txt
libecc-1.1.0.dist-info/RECORD
