Metadata-Version: 2.1
Name: libecc
Version: 1.1.0
Summary: elliptic curves crypto functions
Home-page: https://github.com/aldenml/ecc
Author: Alden Torres
Author-email: aldenml@gmail.com
License: MIT
Project-URL: Bug Tracker, https://github.com/aldenml/ecc/issues
Keywords: elliptic-curves,crypto,hash,sha256,sha512,ed25519,ristretto255,bls12-381,oprf,opaque,pake,apake,authentication,bls-signature,proxy-re-encryption,hkdf,threshold-cryptography,threshold-signature
Classifier: Programming Language :: Python :: 3
Classifier: License :: OSI Approved :: MIT License
Classifier: Topic :: Security :: Cryptography
Requires-Python: >=3.6
License-File: LICENSE
